[
    {
        "id": 900725271878058016,
        "username": "justadev",
        "display name": "justadev | K.O.G."
    },
    {
        "id": 683057987102965782,
        "username": "jesus_perez",
        "display name": "Jesus PL"
    },
    {
        "id": 860937800156708864,
        "username": "brunopgalvao",
        "display name": "&bruno"
    },
    {
        "id": 497820623607824385,
        "username": "xd_abi",
        "display name": "Abinayan Sureskumar"
    },
    {
        "id": 832639594990141539,
        "username": "_magicsheep",
        "display name": "MagicSheep"
    },
    {
        "id": 719933189111414877,
        "username": "aless10_10",
        "display name": "Alessio Giannini"
    },
    {
        "id": 429359693576667145,
        "username": ".wariomx",
        "display name": "wario"
    },
    {
        "id": 1070154910324236309,
        "username": "jp_00112",
        "display name": "J"
    },
    {
        "id": 554299023717302282,
        "username": "damantino",
        "display name": "Daniel Perez"
    },
    {
        "id": 747448461561167953,
        "username": "bhargavs1000",
        "display name": "Bhargav S"
    },
    {
        "id": 675265826554904596,
        "username": "_pinzonazul",
        "display name": "Curl"
    },
    {
        "id": 272210013525770240,
        "username": "javier784952",
        "display name": "javier78#AY24-04"
    },
    {
        "id": 344655083465605130,
        "username": "emiliano6962",
        "display name": "Emiliano"
    },
    {
        "id": 572030614434217984,
        "username": "cocoyoon",
        "display name": "raf"
    },
    {
        "id": 833388086124740627,
        "username": "danielwong4144",
        "display name": "daniel"
    },
    {
        "id": 1049254199013158982,
        "username": "luigidg",
        "display name": "luigidg"
    },
    {
        "id": 971799694596526100,
        "username": "ognjen0800",
        "display name": "Ognjen Aleksic"
    },
    {
        "id": 1180001543634825286,
        "username": "blockzeek",
        "display name": "zeek"
    },
    {
        "id": 1055750543483613234,
        "username": "gang.kantapat",
        "display name": "GANG"
    },
    {
        "id": 1231903027028426815,
        "username": "0xsouravm",
        "display name": "Sourav M"
    },
    {
        "id": 476495957073068045,
        "username": "cy0ny",
        "display name": "Adrian"
    },
    {
        "id": 244850701568573440,
        "username": "bogdansandu_",
        "display name": "Bogdan Sandu"
    },
    {
        "id": 469581712733503523,
        "username": "h256",
        "display name": "H"
    },
    {
        "id": 611246115051798538,
        "username": "0xeboth",
        "display name": "emil_bob"
    },
    {
        "id": 902124356841381890,
        "username": "chris.casini",
        "display name": "Christian.Casini"
    },
    {
        "id": 891196331148840982,
        "username": "camaragon",
        "display name": "Cameron A."
    },
    {
        "id": 436532948943241216,
        "username": "asiniscalchi",
        "display name": "ALeSD"
    },
    {
        "id": 1179804872615403551,
        "username": "tobiasdemeco",
        "display name": "Tobias Demeco"
    },
    {
        "id": 709034066586107924,
        "username": "michjord0001",
        "display name": "Michael Jordan"
    },
    {
        "id": 459848219296268299,
        "username": "poppyseeddev",
        "display name": "poppyseedDev"
    },
    {
        "id": 835906961954177044,
        "username": "laurenlee.",
        "display name": "lolocoding"
    },
    {
        "id": 1080769709852610661,
        "username": "kishansagathiya_77214",
        "display name": "Kishan Sagathiya"
    },
    {
        "id": 379802167411867649,
        "username": "patchkientz",
        "display name": "Patch Kientz"
    },
    {
        "id": 936916706570403900,
        "username": "noormohammedb",
        "display name": "Noor"
    },
    {
        "id": 390865427896598529,
        "username": "sobrepere",
        "display name": "Josep"
    },
    {
        "id": 708200446657036308,
        "username": "zhewang",
        "display name": "Zhe Wang"
    },
    {
        "id": 695572607298437120,
        "username": "aideepak",
        "display name": "Deepak Chaudhary"
    },
    {
        "id": 834032989309501460,
        "username": "pgherveou",
        "display name": "pgherveou"
    },
    {
        "id": 690968773049581609,
        "username": "pieri93",
        "display name": "Pierina"
    },
    {
        "id": 894566388046377010,
        "username": "kazu_yokohama",
        "display name": "Kazunobu Ndong"
    },
    {
        "id": 391877914041384961,
        "username": "dhirajs0",
        "display name": "Dhiraj S."
    },
    {
        "id": 881932914344988732,
        "username": "radhaw3f",
        "display name": "radhaw3f"
    },
    {
        "id": 993069822646698005,
        "username": "wassimans",
        "display name": "Wassim"
    },
    {
        "id": 101477905548185600,
        "username": "0xpeg",
        "display name": "Ryan | Parity | HK Cohort"
    },
    {
        "id": 1116634345722097714,
        "username": "theoryzx",
        "display name": "Trevor Chan"
    },
    {
        "id": 627223164522463252,
        "username": "rohitas_bansal",
        "display name": "Rohitas B."
    },
    {
        "id": 763459234632826922,
        "username": "shobhit_goyal",
        "display name": "Shobhit Goyal"
    },
    {
        "id": 833536204636815390,
        "username": "danfranco27",
        "display name": "danfranco27"
    },
    {
        "id": 819992081233346672,
        "username": "vsiless",
        "display name": "Viviana Siless"
    },
    {
        "id": 224660921333579776,
        "username": "pablinux",
        "display name": "Pablo L. (Pablito)"
    },
    {
        "id": 685709742601273387,
        "username": "sree_sana5835",
        "display name": "Sree S."
    },
    {
        "id": 1091306326409359421,
        "username": "jeffreyzzzz",
        "display name": "Jeffreyzzzz"
    },
    {
        "id": 254771968757334016,
        "username": "anny0nn",
        "display name": "Francisco Castilho"
    },
    {
        "id": 867200030221533184,
        "username": "nomadbitcoin",
        "display name": "Yan Luiz"
    },
    {
        "id": 353990468113137675,
        "username": "sarahsalad",
        "display name": "SarahSalad"
    },
    {
        "id": 499679895572447260,
        "username": "rish_kilt",
        "display name": "Rish"
    },
    {
        "id": 418037911095607297,
        "username": "exquisitus9414",
        "display name": "Gianluigi | Kylix Finance"
    },
    {
        "id": 907435463776800858,
        "username": "ent_ninja",
        "display name": "sergei_astapov"
    },
    {
        "id": 447889850276773911,
        "username": "tsolman",
        "display name": "Konstantinos | PBA"
    },
    {
        "id": 281824937180790785,
        "username": "noahjoeris",
        "display name": "Noah"
    },
    {
        "id": 560485454194147329,
        "username": "franjs_",
        "display name": "silva-fj"
    },
    {
        "id": 996849428679892994,
        "username": "sebastianm2482",
        "display name": "Sebastian Miasojed"
    },
    {
        "id": 690918306688794684,
        "username": "devsphere1995",
        "display name": "devsphere"
    },
    {
        "id": 370182921459335168,
        "username": "saumyakaran",
        "display name": "Saumya Karan"
    },
    {
        "id": 813843965316169778,
        "username": "stolbiq",
        "display name": "Irina"
    },
    {
        "id": 1217159055525679250,
        "username": "alex061743",
        "display name": "Alex Leverington"
    },
    {
        "id": 923197289277820938,
        "username": "igorstojanov_",
        "display name": "igorstojanov_"
    },
    {
        "id": 517258144628342785,
        "username": "luka99",
        "display name": "Luka"
    },
    {
        "id": 922246759072272474,
        "username": "hatcheryllc",
        "display name": "Brian Teague | DoubleDutch PBA3"
    },
    {
        "id": 876371718216777728,
        "username": ".kilgort",
        "display name": "Oleg Tyshchenko"
    },
    {
        "id": 451116664994398209,
        "username": "olivailo",
        "display name": "Oli"
    },
    {
        "id": 876130296649613322,
        "username": "ido.flax",
        "display name": "idoflax"
    },
    {
        "id": 1037353683609985075,
        "username": "gabriel.posta",
        "display name": "gabriel.posta"
    },
    {
        "id": 925270697389985853,
        "username": "0xaaavy",
        "display name": "Archana"
    },
    {
        "id": 372573294047789068,
        "username": "baolson9",
        "display name": "baolson9"
    },
    {
        "id": 1261781479080329216,
        "username": "ms1qaz_96412",
        "display name": "Mateusz S"
    },
    {
        "id": 723721307635712021,
        "username": ".heshz",
        "display name": "heshz"
    },
    {
        "id": 658302060973785110,
        "username": "prasad.k",
        "display name": "Prasad"
    },
    {
        "id": 619030383769681931,
        "username": "s7manth",
        "display name": "Sumanth Yalamarty"
    },
    {
        "id": 844893912111644683,
        "username": "adp1603",
        "display name": "Ashish"
    },
    {
        "id": 351487596389728257,
        "username": "arturgontijo",
        "display name": "arturgontijo"
    },
    {
        "id": 598889575645052939,
        "username": "anshalshukla",
        "display name": "Anshal S"
    },
    {
        "id": 524786225232609282,
        "username": "bee344",
        "display name": "bee344"
    },
    {
        "id": 389129955482533889,
        "username": "recrafter",
        "display name": "Rene H\u00fcrter"
    },
    {
        "id": 565746238562238474,
        "username": "pandres95",
        "display name": "Pablo Andr\u00e9s Dorado Su\u00e1rez"
    },
    {
        "id": 913841938178924595,
        "username": "bobaking5804",
        "display name": "Kevin Krone"
    },
    {
        "id": 1235319224424202371,
        "username": "yhamacnu",
        "display name": "yhamacnu"
    },
    {
        "id": 680806404151705620,
        "username": "luca123a",
        "display name": "Luca"
    },
    {
        "id": 596102329053216778,
        "username": "nicohussein",
        "display name": "nhussein"
    },
    {
        "id": 335401151711412224,
        "username": "chotuchaiwala",
        "display name": "Chetany \"chethack\" Bhardwaj"
    },
    {
        "id": 806015658398842920,
        "username": "luke_4312",
        "display name": "Luke_MLabs"
    },
    {
        "id": 879064560697499690,
        "username": "bigtava",
        "display name": "Tiago Tavares \u2b55"
    },
    {
        "id": 402877646427652099,
        "username": ".dheeraj",
        "display name": "Dheeraj"
    },
    {
        "id": 461819816215445514,
        "username": "kentydotcom_ftcs_oct2022",
        "display name": "dr_kent_lau_main_dev_july2023"
    },
    {
        "id": 799407794599886849,
        "username": "nimit61993",
        "display name": "nimit"
    },
    {
        "id": 209138873630982144,
        "username": "cute_wisp",
        "display name": "Chorong Jang"
    },
    {
        "id": 363027980890669066,
        "username": "todor2todorovic",
        "display name": "Todor T."
    },
    {
        "id": 1126084988937457726,
        "username": "niranjan_p",
        "display name": "Niranjan P"
    },
    {
        "id": 649903789234585600,
        "username": "pankaj15",
        "display name": "Pankaj Chaudhary"
    },
    {
        "id": 400072463595339786,
        "username": "vstam1",
        "display name": "Just"
    },
    {
        "id": 1110085556358090782,
        "username": "khudeja.",
        "display name": "Khudeja Khan"
    },
    {
        "id": 488408949737914369,
        "username": "tobben_dev",
        "display name": "Torbj\u00f8rn Ludvigsen"
    },
    {
        "id": 1043718320450457640,
        "username": "adotlex",
        "display name": "a.lex"
    },
    {
        "id": 826826227830489107,
        "username": "0x.prometheus",
        "display name": "prometheus"
    },
    {
        "id": 859514610363924520,
        "username": "mad_angle",
        "display name": "Mad_angle"
    },
    {
        "id": 556021701784240128,
        "username": "rossbulat",
        "display name": "Ross"
    },
    {
        "id": 986597498506313728,
        "username": "rosarp",
        "display name": "Rohit"
    },
    {
        "id": 1182324340721713198,
        "username": "yuxi_sit",
        "display name": "Yuxi"
    },
    {
        "id": 953486602192158831,
        "username": "snowmead",
        "display name": "Snowmead"
    },
    {
        "id": 1344965411472674838,
        "username": "castillaax",
        "display name": "Hrishav"
    },
    {
        "id": 559754666137747486,
        "username": "sumeetweb",
        "display name": "Sumeet Naik"
    },
    {
        "id": 911189963977150475,
        "username": "louisliu91",
        "display name": "Siyu Liu"
    },
    {
        "id": 829372925165043733,
        "username": "eliashezron",
        "display name": "eliashezron"
    },
    {
        "id": 132691037029138432,
        "username": "papaustin",
        "display name": "papaustin"
    },
    {
        "id": 752705810970181702,
        "username": ".distributeddoge",
        "display name": "DistributedDoge"
    },
    {
        "id": 990997409867894815,
        "username": "arturobv",
        "display name": "ArturoBeccarVarela"
    },
    {
        "id": 755891615884771342,
        "username": "asoliman92",
        "display name": "Boda"
    },
    {
        "id": 754840987238400042,
        "username": ".gfox117",
        "display name": "gfox"
    },
    {
        "id": 508620594867208202,
        "username": "salgac",
        "display name": "Dominik Salgovic"
    },
    {
        "id": 481710591052873728,
        "username": "rajraorane",
        "display name": "Raj Raorane"
    },
    {
        "id": 412648781109002260,
        "username": "decentration",
        "display name": "Ramsey (Decentration)"
    },
    {
        "id": 207236182592061442,
        "username": "crypdough.eth",
        "display name": "Zachary Kornberg"
    },
    {
        "id": 557659818748411906,
        "username": "nzt26",
        "display name": "NZT"
    },
    {
        "id": 1068433665920610356,
        "username": "lousydropout",
        "display name": "vincent chan"
    },
    {
        "id": 1157982585398501397,
        "username": "konrad_06239",
        "display name": "Konrad"
    },
    {
        "id": 850595139139534849,
        "username": "barathkanna",
        "display name": "Barath Kanna"
    },
    {
        "id": 368004909825785858,
        "username": "sam17773",
        "display name": "Sam W"
    },
    {
        "id": 197180375653548032,
        "username": "jakerumbles",
        "display name": "Jake Edwards"
    },
    {
        "id": 1184800871582814230,
        "username": "andrew_11306",
        "display name": "Andrew"
    },
    {
        "id": 1003776371639713792,
        "username": "natearmstrong",
        "display name": "NateArmstrong"
    },
    {
        "id": 809397463475290182,
        "username": "moon_reporter",
        "display name": "Josh"
    },
    {
        "id": 935437799283376128,
        "username": "herryho",
        "display name": "herryho"
    },
    {
        "id": 1103997346557198389,
        "username": "celadari",
        "display name": "Kwickbit - Charles-Edouard"
    },
    {
        "id": 351395037084385282,
        "username": "boring32",
        "display name": "Thanos Doukoudakis"
    },
    {
        "id": 986514715767361567,
        "username": "__mathsyy__",
        "display name": "Rafal Mirowski"
    },
    {
        "id": 686623805438820357,
        "username": "parizval",
        "display name": "Parizval.eth"
    },
    {
        "id": 219466848817774593,
        "username": "overkillus",
        "display name": "Maciej \u017byszkiewicz | Parity"
    },
    {
        "id": 632867154068242442,
        "username": "mugzar",
        "display name": "Mugzar A."
    },
    {
        "id": 847859117409697872,
        "username": "ayevbeosa",
        "display name": "ayevbeosa"
    },
    {
        "id": 102867709846355968,
        "username": "lrazovic",
        "display name": "Leonardo Razovic"
    },
    {
        "id": 879121958204239882,
        "username": "simplestake",
        "display name": "David Corredor"
    },
    {
        "id": 1145756901028663356,
        "username": "myronwill",
        "display name": "Jel"
    },
    {
        "id": 736138529054392360,
        "username": "hailam7735",
        "display name": "Vu Hai Lam"
    },
    {
        "id": 820799654916653057,
        "username": "silvereau",
        "display name": "silvereau"
    },
    {
        "id": 1280516315253182517,
        "username": "leana_49681",
        "display name": "L\u00e9a Na"
    },
    {
        "id": 701444994673672222,
        "username": "darylirl.eth",
        "display name": "darylirl.eth | BlockTrade"
    },
    {
        "id": 386924333353926657,
        "username": "rumeline",
        "display name": "Cl\u00e9ment J"
    },
    {
        "id": 757957148620750868,
        "username": "go123",
        "display name": "ganesh"
    },
    {
        "id": 812907116842319886,
        "username": "professorchaos3925",
        "display name": "David M - aka Prof Chaos"
    },
    {
        "id": 325474688375455744,
        "username": "nbiondini",
        "display name": "NBiondini"
    },
    {
        "id": 931281181780082719,
        "username": "mtnbarreto",
        "display name": "Martin Barreto"
    },
    {
        "id": 384346044919578624,
        "username": "peetzweg",
        "display name": "Philip"
    },
    {
        "id": 784304917501313024,
        "username": "numinous_dokkaebi",
        "display name": "S. Peter C."
    },
    {
        "id": 944007601400741989,
        "username": "developeruche",
        "display name": "developeruche (Nwele Uchenna)"
    },
    {
        "id": 782849129855320104,
        "username": "chief_100",
        "display name": "Chief"
    },
    {
        "id": 782695675141685248,
        "username": "zeroxdreamyyy",
        "display name": "kilian"
    },
    {
        "id": 488043908572643368,
        "username": "wlcvftr",
        "display name": "Thomas Sc."
    },
    {
        "id": 444930820315283456,
        "username": "jslusser",
        "display name": "James Slusser"
    },
    {
        "id": 1226975785978433666,
        "username": "kk.dev",
        "display name": "Karol Kokoszka"
    },
    {
        "id": 526038276574806036,
        "username": "dungeon_master4227",
        "display name": "Dungeon"
    },
    {
        "id": 1178029900272242688,
        "username": "michailleroux",
        "display name": "Michail Le Roux"
    },
    {
        "id": 977660369009012766,
        "username": "soloking1412",
        "display name": "soloking"
    },
    {
        "id": 542710416044982272,
        "username": "fiono11",
        "display name": "Fiono"
    },
    {
        "id": 670255087389769738,
        "username": "tusharojha",
        "display name": "tusharojha"
    },
    {
        "id": 726275131994800258,
        "username": "caxqz",
        "display name": "Carlos Queiroz"
    },
    {
        "id": 1002488458062868521,
        "username": "bearlovesbull",
        "display name": "bearlovesbull"
    },
    {
        "id": 377032206901837834,
        "username": "spinlocker",
        "display name": "micha\u0142"
    },
    {
        "id": 846325048934400000,
        "username": "quietbk",
        "display name": "Dane B."
    },
    {
        "id": 624190110287790080,
        "username": "_gpestana",
        "display name": "gpestana"
    },
    {
        "id": 1342759924190416918,
        "username": "loan_master",
        "display name": "Nicolai F"
    },
    {
        "id": 972866480226074644,
        "username": "hgminerva",
        "display name": "hgminerva"
    },
    {
        "id": 699100116702855220,
        "username": "j3rga",
        "display name": "Edgar Salinas"
    },
    {
        "id": 194833067012128768,
        "username": "_marcus",
        "display name": "marcus"
    },
    {
        "id": 1124641956694331462,
        "username": "raf4547",
        "display name": "Rapha\u00ebl J."
    },
    {
        "id": 694756019355516959,
        "username": "bryanborck",
        "display name": "bry"
    },
    {
        "id": 327843560726462474,
        "username": "sinzii",
        "display name": "Thang X. Vu"
    },
    {
        "id": 1059762934332543047,
        "username": "_kernelkennethg",
        "display name": "KernelKennethG"
    },
    {
        "id": 476512845891371050,
        "username": "alexrp7",
        "display name": "alexrp"
    },
    {
        "id": 1302915581825257484,
        "username": "rajuano_",
        "display name": "Ramiro N"
    },
    {
        "id": 1236731499458465862,
        "username": "mahavirdash",
        "display name": "Mahavir Ganapati Dash"
    },
    {
        "id": 420137353676324875,
        "username": "muracadev",
        "display name": "Matteo D. Muraca"
    },
    {
        "id": 808839253324726273,
        "username": "dontelmo",
        "display name": "Igor"
    },
    {
        "id": 1184134010549583984,
        "username": "timdobie_86973",
        "display name": "Tim Dobie"
    },
    {
        "id": 703411044105846805,
        "username": "jjmiranda.",
        "display name": "JJMiranda"
    },
    {
        "id": 1118841552937156639,
        "username": "max_hic",
        "display name": "Max_HIC"
    },
    {
        "id": 966655026032443392,
        "username": "nikita_gugale",
        "display name": "nikita_gugale"
    },
    {
        "id": 354264230343606292,
        "username": "trantorian",
        "display name": "Eliot McNab"
    },
    {
        "id": 821058955820269598,
        "username": "tomasz_j94",
        "display name": "Tomasz J"
    },
    {
        "id": 677988313319211037,
        "username": "villagefarmer",
        "display name": "Raphael Nembhard"
    },
    {
        "id": 966499596106883092,
        "username": "oliverenciso",
        "display name": "Oliver E."
    },
    {
        "id": 262893672457043968,
        "username": "miotti01",
        "display name": "MioTTi01"
    },
    {
        "id": 1023654000471593041,
        "username": "flamuri",
        "display name": "Flamuri"
    },
    {
        "id": 753025146096189502,
        "username": "alejo.eth",
        "display name": "Alejo"
    },
    {
        "id": 700348582070583486,
        "username": "josepgarces",
        "display name": "Josep I King Garc\u00e9s"
    },
    {
        "id": 258700974921613312,
        "username": "a6e7",
        "display name": "Anasse"
    },
    {
        "id": 450723766939549696,
        "username": "niftesty",
        "display name": "niftesty"
    },
    {
        "id": 959677278659428374,
        "username": "chralt1998",
        "display name": "Chris"
    },
    {
        "id": 693221963044356157,
        "username": "oac1771",
        "display name": "Omar Carey"
    },
    {
        "id": 1064957832157470820,
        "username": "sachin.dagrawal1983",
        "display name": "sachin.dagrawal1983"
    },
    {
        "id": 477774564663754754,
        "username": "shreyas0",
        "display name": "Shreyas Kura Subramanya"
    },
    {
        "id": 1087015309115920415,
        "username": "olliepop0",
        "display name": "tom"
    },
    {
        "id": 389717709258096640,
        "username": "allochi",
        "display name": "Ali Anwar"
    },
    {
        "id": 525986145721647105,
        "username": "_rustghost_",
        "display name": "VJay"
    },
    {
        "id": 919857443729719328,
        "username": "timon1747",
        "display name": "TimoN"
    },
    {
        "id": 799575445896298558,
        "username": "daiagi",
        "display name": "Luke"
    },
    {
        "id": 368837948403089408,
        "username": "kilogold",
        "display name": "Kelvin Bonilla (PBA Berkley)"
    },
    {
        "id": 1216450891251716198,
        "username": "logosalgo",
        "display name": "Christos Nikolaou"
    },
    {
        "id": 382270392129028096,
        "username": "mathis_wellmann",
        "display name": "Mathis Wellmann"
    },
    {
        "id": 693889690578845826,
        "username": "andreydodonov",
        "display name": "Andrey D."
    },
    {
        "id": 757783770861535255,
        "username": "facundofarall",
        "display name": "Facundo"
    },
    {
        "id": 1202693516531343422,
        "username": "helixstreet.io",
        "display name": "Tom | helixstreet.io"
    },
    {
        "id": 1225513589394378872,
        "username": "owahyudi",
        "display name": "O Wahyudi"
    },
    {
        "id": 1161613232193159269,
        "username": "ewogg",
        "display name": "Erin W."
    },
    {
        "id": 183633535020564481,
        "username": "poisonphang",
        "display name": "Connor Davis | Union"
    },
    {
        "id": 869444323819798608,
        "username": "felixchicago",
        "display name": "FelixChicago"
    },
    {
        "id": 627136132672389162,
        "username": "sheetalojha",
        "display name": "SheetalOjha"
    },
    {
        "id": 492675644438740992,
        "username": "szego",
        "display name": "Szego"
    },
    {
        "id": 127611081546792960,
        "username": "apocalam",
        "display name": "Cisco"
    },
    {
        "id": 960056790140207106,
        "username": "code0xff",
        "display name": "Jungyong Um"
    },
    {
        "id": 836544443179597895,
        "username": "mtca.",
        "display name": "Marcelo A."
    },
    {
        "id": 1314562869769015307,
        "username": "cr.eative.dev_28173",
        "display name": "Florian"
    },
    {
        "id": 1043199376589324349,
        "username": "dastansamat",
        "display name": "dastansam"
    },
    {
        "id": 376152365662732291,
        "username": "teo5616",
        "display name": "Teo"
    },
    {
        "id": 466215681667366922,
        "username": "tomek_w",
        "display name": "Tomek"
    },
    {
        "id": 628169573967069214,
        "username": "fazeel.eth",
        "display name": "Fazeel Usmani"
    },
    {
        "id": 1039620960736788530,
        "username": "valentinaga1",
        "display name": "ValentinaG"
    },
    {
        "id": 454144083993034773,
        "username": "chasechung",
        "display name": "Tin Chung | Onchain Citizen"
    },
    {
        "id": 303884734532943872,
        "username": "smehnov",
        "display name": "Alex Smekhnov"
    },
    {
        "id": 777505952089112586,
        "username": "adambrz5627",
        "display name": "adambrz"
    },
    {
        "id": 473912824628772875,
        "username": "calmanz",
        "display name": "ZCalman"
    },
    {
        "id": 873073308768292874,
        "username": "gedeanta",
        "display name": "gedeAnta"
    },
    {
        "id": 367658047859982336,
        "username": "abraham03929",
        "display name": "Abraham Omadoye"
    },
    {
        "id": 690342375431995613,
        "username": "luiz_lvj",
        "display name": "Luiz Vasconcelos Junior"
    },
    {
        "id": 354001424146759692,
        "username": "raxon9940",
        "display name": "Nacho Hernandez"
    },
    {
        "id": 401021167227633664,
        "username": "wonggw123",
        "display name": "Kyubey"
    },
    {
        "id": 1091653538611990528,
        "username": "johnvoronov",
        "display name": "this_john"
    },
    {
        "id": 1091349077557522522,
        "username": "m_rmk",
        "display name": "Maks Ramanenkau"
    },
    {
        "id": 377260572171042817,
        "username": "frankmangone",
        "display name": "frankmangone"
    },
    {
        "id": 519062838380068895,
        "username": "jytey2004",
        "display name": "Jia Ye | ByteLuv"
    },
    {
        "id": 691029346688696322,
        "username": "lh17_",
        "display name": "Luiz C."
    },
    {
        "id": 1222210707487981593,
        "username": "skv_1_24887",
        "display name": "Kevin W"
    },
    {
        "id": 741166779145125960,
        "username": "a_mont",
        "display name": "Amont"
    },
    {
        "id": 691274452150779904,
        "username": "web3.5",
        "display name": "Serge"
    },
    {
        "id": 239453144478646273,
        "username": "kwar13",
        "display name": "kwar13"
    },
    {
        "id": 1007192545840869398,
        "username": "ebmarcel",
        "display name": "Marcel"
    },
    {
        "id": 730306488144494602,
        "username": "gafinetwork",
        "display name": "Gafi Network"
    },
    {
        "id": 695104448674005013,
        "username": "mennatnaga",
        "display name": "Menna Aboelnaga"
    },
    {
        "id": 386651275980439552,
        "username": "juan.girini",
        "display name": "Juan | Ideal Labs"
    },
    {
        "id": 179333716768849930,
        "username": "cellis",
        "display name": "Alex S."
    },
    {
        "id": 767046377683288064,
        "username": "nescampos",
        "display name": "N\u00e9stor Campos"
    },
    {
        "id": 1024170961660018728,
        "username": "maggi2712",
        "display name": "Megha"
    },
    {
        "id": 359863938541813780,
        "username": "dutragus",
        "display name": "Gustavo D."
    },
    {
        "id": 494286825746333716,
        "username": "valenfernand",
        "display name": "valenfernand"
    },
    {
        "id": 219856741205016576,
        "username": "juanirios99",
        "display name": "Juan Ignacio Rios"
    },
    {
        "id": 404855589353816084,
        "username": "indigau",
        "display name": "Harry Tran"
    },
    {
        "id": 509145930419929089,
        "username": "f4b0555",
        "display name": "F4B"
    },
    {
        "id": 128370525746626560,
        "username": "niklabh",
        "display name": "Nikhil Ranjan"
    },
    {
        "id": 499524027052720128,
        "username": "krystian50",
        "display name": "Krystian Fras"
    },
    {
        "id": 886249907650981888,
        "username": "bchief",
        "display name": "Mohit"
    },
    {
        "id": 592707447127539712,
        "username": "xakep1101",
        "display name": "MBrozhko34"
    },
    {
        "id": 692543580375351326,
        "username": "polkaleo",
        "display name": "Leo | BR | protocol"
    },
    {
        "id": 362242181777326081,
        "username": "skymanone",
        "display name": "gherman"
    },
    {
        "id": 479985106040127501,
        "username": "abhiraj_mengade",
        "display name": "Abhiraj"
    },
    {
        "id": 690257335599628309,
        "username": "0xpasta",
        "display name": "Husni R"
    },
    {
        "id": 357374821039996940,
        "username": "hakmark__",
        "display name": "Marek H"
    },
    {
        "id": 515888980114538506,
        "username": "luizv",
        "display name": "Luiz Veloso"
    },
    {
        "id": 618871151396913162,
        "username": "tomtom5807",
        "display name": "TomTom"
    },
    {
        "id": 645637733519327266,
        "username": "rikkard29",
        "display name": "Michael Absolon"
    },
    {
        "id": 574974628179738674,
        "username": "ilariaen",
        "display name": "Ilaria"
    },
    {
        "id": 173828910453096448,
        "username": "krayt78",
        "display name": "Ludovic Domingues"
    },
    {
        "id": 813729849591726120,
        "username": "issa_kalonji",
        "display name": "issa_kalonji"
    },
    {
        "id": 926147514367893595,
        "username": "_no_one_name_",
        "display name": "Dima Babenko"
    },
    {
        "id": 425457825498660864,
        "username": "hette__",
        "display name": "charles"
    },
    {
        "id": 740822110049665066,
        "username": "andy2046",
        "display name": "andy2046"
    },
    {
        "id": 836159339467243532,
        "username": "dragan3",
        "display name": "Dragan"
    },
    {
        "id": 1143527134598545519,
        "username": "voluptuouships_49093",
        "display name": "Tommy"
    },
    {
        "id": 760177095627374633,
        "username": "pm9757",
        "display name": "Parth"
    },
    {
        "id": 1004370745096413314,
        "username": "filippoweb3",
        "display name": "filippoweb3"
    },
    {
        "id": 821137465708380171,
        "username": "_thorking_",
        "display name": "Jose Pedro L."
    },
    {
        "id": 760018403343466506,
        "username": "dudo50",
        "display name": "Dusan Morhac"
    },
    {
        "id": 1178264335794057218,
        "username": "albertwongw2",
        "display name": "Albertwongw2"
    },
    {
        "id": 826061913217171487,
        "username": "leapalazzolo",
        "display name": "leapalazzolo"
    },
    {
        "id": 1133418603434213437,
        "username": "trustlessly_verified",
        "display name": "Cameron"
    },
    {
        "id": 801176167515684904,
        "username": "aaron.bassett",
        "display name": "Aaron Bassett"
    },
    {
        "id": 754272384567083118,
        "username": "ballantines_pm",
        "display name": "Paul M."
    },
    {
        "id": 710663166262247475,
        "username": "reed987",
        "display name": "Przem"
    },
    {
        "id": 640557526647308338,
        "username": "dvdplassie",
        "display name": "Daan van der Plas"
    },
    {
        "id": 316582306242625537,
        "username": "lu.bubba",
        "display name": "Mykyta (Nikita) L"
    },
    {
        "id": 594409127535706120,
        "username": "leo.custodio",
        "display name": "Leonardo C"
    },
    {
        "id": 690996024323604520,
        "username": "0_mica_0",
        "display name": "0_mica_0"
    },
    {
        "id": 699300103843741696,
        "username": "bekkkaa",
        "display name": "Bekka"
    },
    {
        "id": 481690828801310720,
        "username": "realnimish",
        "display name": "Nimish Agrawal"
    },
    {
        "id": 693981874397118495,
        "username": "tinchoh",
        "display name": "Tincho"
    },
    {
        "id": 1321217759799017482,
        "username": "davidcgv",
        "display name": "David C."
    },
    {
        "id": 818494264622186496,
        "username": "mberguer",
        "display name": "Martin"
    },
    {
        "id": 693048360344748098,
        "username": "miquelcabot",
        "display name": "Miquel Cabot"
    },
    {
        "id": 341917354831118338,
        "username": "munificent6864",
        "display name": "munificent"
    },
    {
        "id": 334252448036159488,
        "username": "viktaur",
        "display name": "Victor"
    },
    {
        "id": 734257858685960192,
        "username": "gianalarcon",
        "display name": "GianM"
    },
    {
        "id": 136215798111928320,
        "username": "cardotrejos",
        "display name": "Ricardo Trejos"
    },
    {
        "id": 961265753674358796,
        "username": "replghost",
        "display name": "replghost"
    },
    {
        "id": 267570562711158797,
        "username": "abhijana",
        "display name": "abhijana"
    },
    {
        "id": 748898467174285333,
        "username": "adelarja",
        "display name": "adelarja"
    },
    {
        "id": 965872765259370496,
        "username": "gupnik_",
        "display name": "gupnik"
    },
    {
        "id": 692082260874231818,
        "username": "da3vm",
        "display name": "Daev Mithran"
    },
    {
        "id": 773213356441993247,
        "username": "tommy97_",
        "display name": "Tom\u00e1s Senovilla"
    },
    {
        "id": 1094670426455674921,
        "username": "tomwuadvice",
        "display name": "yong"
    },
    {
        "id": 600076939453268018,
        "username": "driemworks",
        "display name": "Tony"
    },
    {
        "id": 325717384130199552,
        "username": "isubotic",
        "display name": "Ivan Subotic"
    },
    {
        "id": 495930748810035201,
        "username": "citolito.",
        "display name": "mario m."
    },
    {
        "id": 548618495383044129,
        "username": "danicuki",
        "display name": "danicuki"
    },
    {
        "id": 663059743421759497,
        "username": "keshg",
        "display name": "k Gunjan"
    },
    {
        "id": 265635002413219840,
        "username": "lecascyril",
        "display name": "Cyril Castagnet"
    },
    {
        "id": 779841926051528714,
        "username": "tymat31337",
        "display name": "Hiro Protagonist"
    },
    {
        "id": 442001256085454888,
        "username": "flaggedlasso",
        "display name": "Michael Rastadmehr"
    },
    {
        "id": 802036495468855356,
        "username": "gravytrain89",
        "display name": "GravityGravyTrain"
    },
    {
        "id": 819213798165577818,
        "username": "kirillpisariev",
        "display name": "Kirill Pisariev"
    },
    {
        "id": 844247947708858419,
        "username": "diegotristain",
        "display name": "Diego Correa Tristain"
    },
    {
        "id": 813253025064943648,
        "username": "chuacw",
        "display name": "Chee-Wee Chua"
    },
    {
        "id": 301446467468525569,
        "username": "yungbeef4.2",
        "display name": "Zachary \"Yung Beef\" Edwards"
    },
    {
        "id": 496849090018279464,
        "username": "leopham4259",
        "display name": "Leo Pham"
    },
    {
        "id": 675928997703712788,
        "username": "julio75012",
        "display name": "Jules LEIDELINGER"
    },
    {
        "id": 321376039135870976,
        "username": "nemanya21",
        "display name": "Nemanja M"
    },
    {
        "id": 725173074986663966,
        "username": ".johnyu",
        "display name": "John Yu"
    },
    {
        "id": 533782625404321813,
        "username": "johandroid",
        "display name": "JohanDroid"
    },
    {
        "id": 701227372774686813,
        "username": "gianniman",
        "display name": "Gianniman"
    },
    {
        "id": 1013616686945030245,
        "username": "hippiestank",
        "display name": "Corey H"
    },
    {
        "id": 989120080505864233,
        "username": "tiwipaddler",
        "display name": "Seliana"
    },
    {
        "id": 307217062932119554,
        "username": "lucas.delellis",
        "display name": "Lucas de Lellis"
    },
    {
        "id": 1014749963382685726,
        "username": "marschou",
        "display name": "ZHOU Yubo (Mars)"
    },
    {
        "id": 942690909038997545,
        "username": "sachingurjar",
        "display name": "Sachin Gurjar"
    },
    {
        "id": 496233734765412352,
        "username": "sixthedave",
        "display name": "-"
    },
    {
        "id": 894065541864644639,
        "username": "paloma_pe",
        "display name": "PalomaP"
    },
    {
        "id": 737446811295285369,
        "username": "smontero",
        "display name": "smontero"
    },
    {
        "id": 177546433933606913,
        "username": "wolfenheimm",
        "display name": "Jesse Rafters"
    },
    {
        "id": 813796875274682380,
        "username": "biosaward",
        "display name": "biosaward"
    },
    {
        "id": 924224558121226250,
        "username": "marcodotio",
        "display name": "MarcoDotIO"
    },
    {
        "id": 557195378831917085,
        "username": "cj13th",
        "display name": "Connor Campbell"
    },
    {
        "id": 1169200913374785560,
        "username": "aliciashortman",
        "display name": "Alicia S."
    },
    {
        "id": 1258067207162953830,
        "username": "yuri__xyz",
        "display name": "yuri__xyz"
    },
    {
        "id": 467291448254005259,
        "username": "matjazonline",
        "display name": "Matjaz H"
    },
    {
        "id": 983269059263082526,
        "username": "xcavate",
        "display name": "richard-Xcavate"
    },
    {
        "id": 738068278051864647,
        "username": "sebliu",
        "display name": "Seb"
    },
    {
        "id": 495764464604413972,
        "username": "irvinxyz",
        "display name": "Irvin"
    },
    {
        "id": 847221227861180446,
        "username": "walquerx",
        "display name": "Exodo"
    },
    {
        "id": 687904668810084372,
        "username": "benjaminsalon",
        "display name": "BenjaminSalon"
    },
    {
        "id": 1187317362551169045,
        "username": "marioschraepen_72989",
        "display name": "MarioS"
    },
    {
        "id": 299576341420965889,
        "username": "fritz_.",
        "display name": "Fritz"
    },
    {
        "id": 1056317677880221746,
        "username": ".badery",
        "display name": "Bader Youssef"
    },
    {
        "id": 842682117690884096,
        "username": "rohitbhandari0880",
        "display name": "Rohit Bhandari"
    },
    {
        "id": 964529281365602384,
        "username": "0xjunha",
        "display name": "Junha P."
    },
    {
        "id": 359627444568719360,
        "username": "mar1dev",
        "display name": "marin"
    },
    {
        "id": 800725509692588033,
        "username": "altimario",
        "display name": "AltiMario"
    },
    {
        "id": 755138736127344783,
        "username": "carla_muc_j",
        "display name": "Carla"
    },
    {
        "id": 282165706995531776,
        "username": "tarekkma",
        "display name": "Tarek"
    },
    {
        "id": 302250823461634049,
        "username": "meng0581",
        "display name": "Tugii"
    },
    {
        "id": 844498270659018762,
        "username": "jv27033",
        "display name": "jv2"
    },
    {
        "id": 278098507561172992,
        "username": "arjanvaneersel",
        "display name": "Arjan van Eersel"
    },
    {
        "id": 395981331064160257,
        "username": "synaptic0n",
        "display name": "Riccardo Tosti"
    },
    {
        "id": 1202633520590102570,
        "username": "valentinaga1_23577",
        "display name": "valentinaga1"
    },
    {
        "id": 396956527564685324,
        "username": "ngduo",
        "display name": "Nghia Duong | Dan"
    },
    {
        "id": 496685464347082753,
        "username": "rostadev",
        "display name": "Rosta Litovkin"
    },
    {
        "id": 572898282536173600,
        "username": "tallesborges_",
        "display name": "tallesborges"
    },
    {
        "id": 423858007001268226,
        "username": "prof._horacio_clueless_ph.d.",
        "display name": "prof. Horacio Clueless Ph.D."
    },
    {
        "id": 468639577075220481,
        "username": "aaron_hk",
        "display name": "aaron"
    },
    {
        "id": 616119000597921792,
        "username": "dgrayman97",
        "display name": "dgrayman97"
    },
    {
        "id": 834394687346966590,
        "username": "zsofi_m",
        "display name": "Zs\u00f3fi | PBA"
    },
    {
        "id": 1048023289907392562,
        "username": "ank4n",
        "display name": "Ankan"
    },
    {
        "id": 368461699017342976,
        "username": "conr2d",
        "display name": "Jeeyong Um"
    },
    {
        "id": 1080135048696692847,
        "username": "marta.pba",
        "display name": "Marta (GMT)"
    },
    {
        "id": 689879047517503501,
        "username": "skoszuta",
        "display name": "sebastian"
    },
    {
        "id": 636128120407064588,
        "username": "thekatia",
        "display name": "katia"
    },
    {
        "id": 959882892140478475,
        "username": "nutmgn",
        "display name": "Megan Sharon"
    },
    {
        "id": 1182953283111890964,
        "username": "paulinecohenv",
        "display name": "Pauline | PBA"
    },
    {
        "id": 294476982043934720,
        "username": "gr8h",
        "display name": "Hesham"
    },
    {
        "id": 1081318801414574081,
        "username": "andrzej.sulkowski",
        "display name": "Andrzej Sulkowski"
    },
    {
        "id": 747834858243620996,
        "username": "hectorb06",
        "display name": "Hector<B>"
    },
    {
        "id": 272093437166223360,
        "username": "kayabanerve",
        "display name": "Kayaba"
    },
    {
        "id": 478343070308630528,
        "username": ".agusrodri",
        "display name": "Agusrodri"
    },
    {
        "id": 1039441687220584489,
        "username": "meng5990",
        "display name": "Mengling"
    },
    {
        "id": 863427115709104128,
        "username": "acai4620",
        "display name": "Acai"
    },
    {
        "id": 414770832062283787,
        "username": "wirednkod",
        "display name": "nikos | PBA"
    },
    {
        "id": 764507708690530404,
        "username": "alissa18_",
        "display name": "Alissa V"
    },
    {
        "id": 587378166390325268,
        "username": "protocolwhisper.eth",
        "display name": "protocolwhisper.eth"
    },
    {
        "id": 930463956533919784,
        "username": "nofo1",
        "display name": "Noah"
    },
    {
        "id": 289888554748739586,
        "username": "fitzygold",
        "display name": "Thomas F"
    },
    {
        "id": 1165649893805805570,
        "username": "codingshthefounder",
        "display name": "Fred"
    },
    {
        "id": 351035319392665600,
        "username": "jegorkin",
        "display name": "Jegor"
    },
    {
        "id": 863864992856145920,
        "username": "mrisholukamba",
        "display name": "MHL"
    },
    {
        "id": 469593062004359169,
        "username": "hao_ding",
        "display name": "Harold | DIN"
    },
    {
        "id": 618790696454848512,
        "username": "prathamesh_m",
        "display name": "Prathamesh"
    },
    {
        "id": 712889084514795571,
        "username": "jgyy",
        "display name": "jeffrey goh"
    },
    {
        "id": 792633797845450754,
        "username": "yerbol1111",
        "display name": "yerbol1111"
    },
    {
        "id": 524349661323198474,
        "username": "kiron79",
        "display name": "Kiron"
    }
]